mediatr/__init__.py
mediatr/_version.py
mediatr/exceptions.py
mediatr/mediator.py
mediatr_ez-1.0.7.dist-info/LICENSE.APACHE2
mediatr_ez-1.0.7.dist-info/LICENSE.mit
mediatr_ez-1.0.7.dist-info/LICENSE.txt
mediatr_ez-1.0.7.dist-info/METADATA
mediatr_ez-1.0.7.dist-info/WHEEL
mediatr_ez-1.0.7.dist-info/top_level.txt
mediatr_ez-1.0.7.dist-info/RECORD
