Metadata-Version: 2.1
Name: mediatr-ez
Version: 1.0.7
Summary: Mediator project
Author-email: Anh Khoa <khoava.dev@gmail.com>
Project-URL: Homepage, https://github.com/vuanhkhoadev/mediatr_py_custom
Keywords: mediatr,mediator,flask-mediator,mediator-ez
Classifier: License :: OSI Approved :: MIT License
Classifier: Programming Language :: Python
Classifier: Programming Language :: Python :: 3
Requires-Python: >=3.8
License-File: LICENSE.APACHE2
License-File: LICENSE.mit
License-File: LICENSE.txt
Requires-Dist: feedparser (>=5.2.0)
Requires-Dist: injector (>=0.20.1)
Requires-Dist: html2text
Requires-Dist: tomli ; python_version < "3.11"
Provides-Extra: dev
Requires-Dist: black ; extra == 'dev'
Requires-Dist: bumpver ; extra == 'dev'
Requires-Dist: isort ; extra == 'dev'
Requires-Dist: pip-tools ; extra == 'dev'
Requires-Dist: pytest ; extra == 'dev'
